[
  {
    "id": "sql-dml_001",
    "categoryId": "sql-dml",
    "subcategory": "SELECT/COUNT",
    "type": "sql",
    "difficulty": 2,
    "question": "다음 SQL문의 실행 결과 행 수를 쓰시오.",
    "answer": "1",
    "explanation": "AND가 OR보다 우선순위가 높습니다.\n(EMPNO>100 AND SAL>=3000): 200/3000만 해당 → 1건\nOR EMPNO=200: 200이 이미 포함 → 중복제거\n결과: 1행",
    "choices": [
      {
        "label": "1",
        "text": "1",
        "isCorrect": true
      },
      {
        "label": "2",
        "text": "2",
        "isCorrect": false
      },
      {
        "label": "3",
        "text": "3",
        "isCorrect": false
      },
      {
        "label": "4",
        "text": "0",
        "isCorrect": false
      }
    ],
    "source": "pdf",
    "sourceFile": "SQL_기출문제_+_DML_디테일_학습자료_v0.1.pdf",
    "tags": [
      "SQL",
      "SELECT",
      "COUNT",
      "AND",
      "OR",
      "우선순위"
    ],
    "codeSnippet": "[EMP 테이블]\n EMPNO | SAL\n-------+------\n  100  | 1000\n  200  | 3000\n  300  | 1500\n\nSELECT COUNT(*) FROM EMP\nWHERE EMPNO > 100 AND SAL >= 3000\n   OR EMPNO = 200;"
  },
  {
    "id": "sql-dml_002",
    "categoryId": "sql-dml",
    "subcategory": "UNION",
    "type": "sql",
    "difficulty": 1,
    "question": "다음 SQL문의 실행 결과를 작성하시오.",
    "answer": "4\n3\n2\n1",
    "explanation": "UNION은 중복을 제거하고 합칩니다.\nT1: {3,1,4}, T2: {2,4,3}\n합집합: {1,2,3,4}\nORDER BY A DESC → 4,3,2,1",
    "source": "pdf",
    "sourceFile": "SQL_기출문제_+_DML_디테일_학습자료_v0.1.pdf",
    "tags": [
      "SQL",
      "UNION",
      "ORDER BY",
      "집합"
    ],
    "codeSnippet": "[T1 테이블]    [T2 테이블]\n  A             A\n-----         -----\n  3             2\n  1             4\n  4             3\n\nSELECT A FROM T1\nUNION\nSELECT A FROM T2\nORDER BY A DESC;"
  },
  {
    "id": "sql-dml_003",
    "categoryId": "sql-dml",
    "subcategory": "DELETE",
    "type": "sql",
    "difficulty": 1,
    "question": "학생 테이블에서 이름이 '민수'인 튜플을 삭제하는 SQL을 작성하시오.",
    "answer": "DELETE FROM 학생 WHERE 이름 = '민수';",
    "explanation": "DELETE FROM 테이블명 WHERE 조건;\n문자열 비교 시 작은따옴표를 사용합니다.",
    "source": "pdf",
    "sourceFile": "SQL_기출문제_+_DML_디테일_학습자료_v0.1.pdf",
    "tags": [
      "SQL",
      "DELETE",
      "DML"
    ],
    "codeSnippet": "[학생 테이블]\n 학번 | 이름 | 학년\n------+------+-----\n 100  | 민수 |  2\n 200  | 영희 |  3\n 300  | 철수 |  1"
  },
  {
    "id": "sql-dml_004",
    "categoryId": "sql-dml",
    "subcategory": "UPDATE",
    "type": "sql",
    "difficulty": 1,
    "question": "학생 테이블에서 이름이 '민수'인 학생의 이름을 '수철'로 변경하는 SQL을 작성하시오.",
    "answer": "UPDATE 학생 SET 이름 = '수철' WHERE 이름 = '민수';",
    "explanation": "UPDATE 테이블명 SET 컬럼 = 값 WHERE 조건;\nSET으로 변경할 값을 지정하고, WHERE로 대상을 특정합니다.",
    "source": "pdf",
    "sourceFile": "SQL_기출문제_+_DML_디테일_학습자료_v0.1.pdf",
    "tags": [
      "SQL",
      "UPDATE",
      "DML"
    ],
    "codeSnippet": "[학생 테이블]\n 학번 | 이름 | 학년\n------+------+-----\n 100  | 민수 |  2\n 200  | 영희 |  3\n 300  | 철수 |  1"
  },
  {
    "id": "sql-dml_005",
    "categoryId": "sql-dml",
    "subcategory": "GROUP BY/HAVING",
    "type": "sql",
    "difficulty": 2,
    "question": "성적 테이블에서 과목별 평균이 90점 이상인 과목의 이름, 최소점수, 최대점수를 검색하시오.\n[조건] WHERE 사용금지, GROUP BY와 HAVING 필수, 집계함수 사용",
    "answer": "SELECT 과목이름, MIN(점수) AS 최소점수, MAX(점수) AS 최대점수\nFROM 성적\nGROUP BY 과목이름\nHAVING AVG(점수) >= 90",
    "explanation": "GROUP BY로 과목별 그룹화 후, HAVING으로 평균 90 이상 필터링합니다.\nMIN(), MAX()는 집계함수, AS는 별칭입니다.",
    "source": "pdf",
    "sourceFile": "SQL_기출문제_+_DML_디테일_학습자료_v0.1.pdf",
    "tags": [
      "SQL",
      "GROUP BY",
      "HAVING",
      "집계함수",
      "별칭"
    ],
    "codeSnippet": "[성적 테이블]\n 과목코드 | 과목이름   | 점수\n---------+-----------+-----\n 1000    | 데이터베이스 |  95\n 2000    | 운영체제    |  85\n 1000    | 데이터베이스 |  90\n 2000    | 운영체제    |  80\n 3000    | 네트워크    |  92"
  }
]
